{
    "users": [{
            "name": "Trendafil Dabov",
            "phone": "0877415699",
            "description": "Student in Sofia University in specialty Information systems",
            "profice-picture": "IMG_20190902_145714.jpg"
        },
        {
            "name": "Georgi Petrov",
            "phone": "0811143644",
            "description": "Student in Sofia University in specialty Computer science",
            "profice-picture": "1_4wHJdbPgCa-SQvj7l5qsgA.jpg"
        },
        {
            "name": "Ivan Ivanov",
            "phone": "0855214733",
            "description": "Student in Technical University in specialty Computer and software engineering.",
            "profice-picture": "1_4wHJdbPgCa-SQvj7l5qsgA.jpg"
        }
    ]
}